resizer/__init__.py
resizer/resize.py
resizer-0.0.4.dist-info/METADATA
resizer-0.0.4.dist-info/WHEEL
resizer-0.0.4.dist-info/top_level.txt
resizer-0.0.4.dist-info/RECORD
